{
  "directed": true,
  "multigraph": false,
  "graph": {
    "id": "graph_god",
    "schema_version": "1.0"
  },
  "nodes": [
    {
      "task_type": "class",
      "task_identifier": "tasks_config.ExecuteGlobalWorkflow",
      "default_inputs": [
        {
          "name": "path_to_find",
          "value": "/home/esrf/edgar1993a/work/ewoks/edf_data"
        },
        {
          "name": "pattern",
          "value": "*.edf"
        },
        {
          "name": "nfiles",
          "value": 10
        },
        {
          "name": "chunk_size",
          "value": 5
        },
        {
          "name": "config",
          "value": "ewoks_config_cython.json"
        },
        {
          "name": "slurm",
          "value": true
        }
      ],
      "id": "node_god"
    }
  ],
  "links": []
}